mycookie/__init__.py
mycookie/core.py
mycookie-0.0.1.dist-info/METADATA
mycookie-0.0.1.dist-info/WHEEL
mycookie-0.0.1.dist-info/top_level.txt
mycookie-0.0.1.dist-info/RECORD
